wse_exercises/__init__.py
wse_exercises/base/__init__.py
wse_exercises/base/componets.py
wse_exercises/base/enums.py
wse_exercises/base/exercise.py
wse_exercises/base/interfaces.py
wse_exercises/base/mixins.py
wse_exercises/base/task.py
wse_exercises/core/__init__.py
wse_exercises/core/math/__init__.py
wse_exercises/core/math/base/__init__.py
wse_exercises/core/math/base/exercise.py
wse_exercises/core/math/base/services.py
wse_exercises/core/math/base/task_factory.py
wse_exercises/core/math/enums.py
wse_exercises/core/math/exceptions.py
wse_exercises/core/math/exercises.py
wse_exercises/core/math/interfaces.py
wse_exercises/core/math/services/__init__.py
wse_exercises/core/math/services/operand_generator.py
wse_exercises/core/math/task.py
wse_exercises/core/math/task_factories.py
wse_exercises/py.typed
wse_exercises/utils/__init__.py
wse_exercises/utils/logger.py
wse_exercises-1.0.1.dist-info/METADATA
wse_exercises-1.0.1.dist-info/WHEEL
wse_exercises-1.0.1.dist-info/RECORD
