Metadata-Version: 2.3
Name: wse-exercises
Version: 1.0.1
Summary: Exercises for WSE applications
Author: Sergei Mikurov
Author-email: 454004@mail.ru
Requires-Python: >=3.10,<4.0
Classifier: Programming Language :: Python :: 3
Classifier: Programming Language :: Python :: 3.10
Classifier: Programming Language :: Python :: 3.11
Classifier: Programming Language :: Python :: 3.12
Classifier: Programming Language :: Python :: 3.13
Requires-Dist: pydantic (==1.10.22)
